dhee_obs/__init__.py
dhee_obs/client.py
dhee_obs/dhee_logger.py
dhee_obs/dhee_loghandler.py
dheedemo/__init__.py
dheedemo/client.py
dheedemo/dhee_logger.py
dheedemo/dhee_loghandler.py
dheedemo-0.1.0.dist-info/METADATA
dheedemo-0.1.0.dist-info/WHEEL
dheedemo-0.1.0.dist-info/top_level.txt
dheedemo-0.1.0.dist-info/RECORD
